{
  "data": {
    "article": {},
    "attachments": {},
    "author_id": "2047894021457211393",
    "conversation_id": "2052026070678000116",
    "created_at": "2026-05-06T14:07:41.000Z",
    "edit_controls": {
      "editable_until": "2026-05-06T15:07:41.000Z",
      "edits_remaining": 5,
      "is_edit_eligible": false
    },
    "edit_history_tweet_ids": [
      "2052027523937267860"
    ],
    "entities": {
      "mentions": [
        {
          "end": 12,
          "id": "1914766734420279296",
          "start": 0,
          "username": "yangtao1729"
        }
      ]
    },
    "geo": {},
    "id": "2052027523937267860",
    "in_reply_to_user_id": "1914766734420279296",
    "lang": "und",
    "note_tweet": {
      "entities": {}
    },
    "possibly_sensitive": false,
    "public_metrics": {
      "bookmark_count": 0,
      "impression_count": 0,
      "like_count": 0,
      "quote_count": 0,
      "reply_count": 0,
      "retweet_count": 0
    },
    "referenced_tweets": [
      {
        "id": "2052027132948386121",
        "type": "replied_to"
      }
    ],
    "reply_settings": "everyone",
    "text": "@yangtao1729 ok🤤"
  },
  "includes": {
    "media": [
      {
        "height": 1538,
        "media_key": "3_2052027130201231360",
        "public_metrics": {},
        "type": "photo",
        "url": "https://pbs.twimg.com/media/HHpDzYUb0AAVSnx.jpg",
        "width": 1080
      }
    ],
    "tweets": [
      {
        "article": {},
        "attachments": {},
        "author_id": "2047894021457211393",
        "conversation_id": "2052026070678000116",
        "created_at": "2026-05-06T14:07:41.000Z",
        "edit_controls": {
          "editable_until": "2026-05-06T15:07:41.000Z",
          "edits_remaining": 5,
          "is_edit_eligible": false
        },
        "edit_history_tweet_ids": [
          "2052027523937267860"
        ],
        "entities": {
          "mentions": [
            {
              "end": 12,
              "id": "1914766734420279296",
              "start": 0,
              "username": "yangtao1729"
            }
          ]
        },
        "geo": {},
        "id": "2052027523937267860",
        "in_reply_to_user_id": "1914766734420279296",
        "lang": "und",
        "note_tweet": {
          "entities": {}
        },
        "possibly_sensitive": false,
        "public_metrics": {
          "bookmark_count": 0,
          "impression_count": 0,
          "like_count": 0,
          "quote_count": 0,
          "reply_count": 0,
          "retweet_count": 0
        },
        "referenced_tweets": [
          {
            "id": "2052027132948386121",
            "type": "replied_to"
          }
        ],
        "reply_settings": "everyone",
        "text": "@yangtao1729 ok🤤"
      },
      {
        "article": {},
        "attachments": {
          "media_keys": [
            "3_2052027130201231360"
          ]
        },
        "author_id": "1914766734420279296",
        "conversation_id": "2052026070678000116",
        "created_at": "2026-05-06T14:06:07.000Z",
        "edit_controls": {
          "editable_until": "2026-05-06T15:06:07.000Z",
          "edits_remaining": 5,
          "is_edit_eligible": false
        },
        "edit_history_tweet_ids": [
          "2052027132948386121"
        ],
        "entities": {
          "mentions": [
            {
              "end": 16,
              "id": "2047894021457211393",
              "start": 0,
              "username": "FanQie_QianQian"
            }
          ],
          "urls": [
            {
              "display_url": "pic.x.com/8TG2H9rXGe",
              "end": 56,
              "expanded_url": "https://x.com/yangtao1729/status/2052027132948386121/photo/1",
              "media_key": "3_2052027130201231360",
              "start": 33,
              "url": "https://t.co/8TG2H9rXGe"
            }
          ]
        },
        "geo": {},
        "id": "2052027132948386121",
        "in_reply_to_user_id": "2047894021457211393",
        "lang": "und",
        "note_tweet": {
          "entities": {}
        },
        "possibly_sensitive": false,
        "public_metrics": {
          "bookmark_count": 0,
          "impression_count": 0,
          "like_count": 1,
          "quote_count": 0,
          "reply_count": 1,
          "retweet_count": 0
        },
        "referenced_tweets": [
          {
            "id": "2052026070678000116",
            "type": "replied_to"
          }
        ],
        "reply_settings": "everyone",
        "text": "@FanQie_QianQian 🤤🤤🤤🤤（👁👁👁👁👁👁👁👁👁） https://t.co/8TG2H9rXGe"
      }
    ],
    "users": [
      {
        "created_at": "2026-04-25T04:22:51.000Z",
        "description": "重生之8.0\n11年 順女 LGBTQ全友好 前世互關尋回",
        "entities": {
          "url": {
            "urls": [
              {
                "display_url": "ngl.link/_tomato._.fanq…",
                "end": 23,
                "expanded_url": "https://ngl.link/_tomato._.fanqie_1",
                "start": 0,
                "url": "https://t.co/JbrJBgq8ZL"
              }
            ]
          }
        },
        "id": "2047894021457211393",
        "location": "🚪",
        "name": "飯企鵝8.0",
        "pinned_tweet_id": "2051753420537954589",
        "profile_image_url": "https://pbs.twimg.com/profile_images/2047913417026256896/nhgiZEyi_normal.jpg",
        "protected": false,
        "public_metrics": {
          "followers_count": 319,
          "following_count": 14,
          "like_count": 369,
          "listed_count": 1,
          "media_count": 11,
          "tweet_count": 127
        },
        "url": "https://t.co/JbrJBgq8ZL",
        "username": "FanQie_QianQian",
        "verified": false
      },
      {
        "created_at": "2025-04-22T19:42:30.000Z",
        "description": "（（）♂男（（）  什么都不想写。（）（）（）（）（）可以不爱，不能太爱。\n我很好相处的诶嘿（👁️‍🗨️👁️‍🗨️）\n        永远的@XiShangguan",
        "entities": {
          "description": {
            "mentions": [
              {
                "end": 82,
                "start": 70,
                "username": "XiShangguan"
              }
            ]
          },
          "url": {
            "urls": [
              {
                "display_url": "ngl.link/yangtao1729",
                "end": 23,
                "expanded_url": "https://ngl.link/yangtao1729",
                "start": 0,
                "url": "https://t.co/MjsQHi05n5"
              }
            ]
          }
        },
        "id": "1914766734420279296",
        "location": "下界",
        "name": "白骑士与刺玫瑰",
        "pinned_tweet_id": "2051367712023285966",
        "profile_image_url": "https://pbs.twimg.com/profile_images/2000433652501774336/VpJJuMMx_normal.jpg",
        "protected": false,
        "public_metrics": {
          "followers_count": 133,
          "following_count": 210,
          "like_count": 15591,
          "listed_count": 0,
          "media_count": 223,
          "tweet_count": 7632
        },
        "url": "https://t.co/MjsQHi05n5",
        "username": "yangtao1729",
        "verified": false
      }
    ]
  }
}