{
  "data": {
    "article": {},
    "attachments": {},
    "author_id": "2047894021457211393",
    "conversation_id": "2062571409214464439",
    "created_at": "2026-06-04T22:41:05.000Z",
    "edit_controls": {
      "editable_until": "2026-06-04T23:41:05.000Z",
      "edits_remaining": 5,
      "is_edit_eligible": false
    },
    "edit_history_tweet_ids": [
      "2062665973174551009"
    ],
    "entities": {
      "mentions": [
        {
          "end": 11,
          "id": "2029061443568713731",
          "start": 0,
          "username": "maoxianACT"
        }
      ]
    },
    "geo": {},
    "id": "2062665973174551009",
    "in_reply_to_user_id": "2029061443568713731",
    "lang": "zh",
    "note_tweet": {
      "entities": {}
    },
    "possibly_sensitive": false,
    "public_metrics": {
      "bookmark_count": 0,
      "impression_count": 0,
      "like_count": 0,
      "quote_count": 0,
      "reply_count": 0,
      "retweet_count": 0
    },
    "referenced_tweets": [
      {
        "id": "2062571409214464439",
        "type": "replied_to"
      }
    ],
    "reply_settings": "other",
    "text": "@maoxianACT 輕鬆繃住"
  },
  "includes": {
    "media": [
      {
        "height": 2048,
        "media_key": "3_2062571402881056768",
        "public_metrics": {},
        "type": "photo",
        "url": "https://pbs.twimg.com/media/HJ-5w1CawAArHww.jpg",
        "width": 943
      }
    ],
    "tweets": [
      {
        "article": {},
        "attachments": {},
        "author_id": "2047894021457211393",
        "conversation_id": "2062571409214464439",
        "created_at": "2026-06-04T22:41:05.000Z",
        "edit_controls": {
          "editable_until": "2026-06-04T23:41:05.000Z",
          "edits_remaining": 5,
          "is_edit_eligible": false
        },
        "edit_history_tweet_ids": [
          "2062665973174551009"
        ],
        "entities": {
          "mentions": [
            {
              "end": 11,
              "id": "2029061443568713731",
              "start": 0,
              "username": "maoxianACT"
            }
          ]
        },
        "geo": {},
        "id": "2062665973174551009",
        "in_reply_to_user_id": "2029061443568713731",
        "lang": "zh",
        "note_tweet": {
          "entities": {}
        },
        "possibly_sensitive": false,
        "public_metrics": {
          "bookmark_count": 0,
          "impression_count": 0,
          "like_count": 0,
          "quote_count": 0,
          "reply_count": 0,
          "retweet_count": 0
        },
        "referenced_tweets": [
          {
            "id": "2062571409214464439",
            "type": "replied_to"
          }
        ],
        "reply_settings": "other",
        "text": "@maoxianACT 輕鬆繃住"
      },
      {
        "article": {},
        "attachments": {
          "media_keys": [
            "3_2062571402881056768"
          ]
        },
        "author_id": "2029061443568713731",
        "conversation_id": "2062571409214464439",
        "created_at": "2026-06-04T16:25:19.000Z",
        "edit_controls": {
          "editable_until": "2026-06-04T17:25:19.000Z",
          "edits_remaining": 5,
          "is_edit_eligible": true
        },
        "edit_history_tweet_ids": [
          "2062571409214464439"
        ],
        "entities": {
          "urls": [
            {
              "display_url": "pic.x.com/cpl6dHwbuf",
              "end": 34,
              "expanded_url": "https://x.com/maoxianACT/status/2062571409214464439/photo/1",
              "media_key": "3_2062571402881056768",
              "start": 11,
              "url": "https://t.co/cpl6dHwbuf"
            }
          ]
        },
        "geo": {},
        "id": "2062571409214464439",
        "lang": "zh",
        "note_tweet": {
          "entities": {}
        },
        "possibly_sensitive": false,
        "public_metrics": {
          "bookmark_count": 0,
          "impression_count": 1258,
          "like_count": 33,
          "quote_count": 0,
          "reply_count": 3,
          "retweet_count": 0
        },
        "reply_settings": "other",
        "text": "我对象给我发的红包。 https://t.co/cpl6dHwbuf"
      }
    ],
    "users": [
      {
        "created_at": "2026-04-25T04:22:51.000Z",
        "description": "重生之8.0\n11年 順女 LGBTQ全友好 前世互關尋回\n寶寶 @7q46843886669",
        "entities": {
          "description": {
            "mentions": [
              {
                "end": 47,
                "start": 33,
                "username": "7q46843886669"
              }
            ]
          },
          "url": {
            "urls": [
              {
                "display_url": "ngl.link/_tomato._.fanq…",
                "end": 23,
                "expanded_url": "https://ngl.link/_tomato._.fanqie_1",
                "start": 0,
                "url": "https://t.co/JbrJBgq8ZL"
              }
            ]
          }
        },
        "id": "2047894021457211393",
        "name": "飯企鵝8.0",
        "pinned_tweet_id": "2051753420537954589",
        "profile_image_url": "https://pbs.twimg.com/profile_images/2057140948434649088/mo_BXY2p_normal.jpg",
        "protected": false,
        "public_metrics": {
          "followers_count": 533,
          "following_count": 31,
          "like_count": 967,
          "listed_count": 1,
          "media_count": 32,
          "tweet_count": 413
        },
        "url": "https://t.co/JbrJBgq8ZL",
        "username": "FanQie_QianQian",
        "verified": false
      },
      {
        "created_at": "2026-03-04T05:08:48.000Z",
        "description": "🤍前世@maoxian1527 | kitty live system | 看心情互fo | 记录自己的随笔故事 | 摄影 | 🍥🏳️‍⚧️🤍@maoxian2010\n姐姐@OuO_QwQg 对象@Meph4786 \n閨蜜@tangeorange 老爸 @Wilf_Lin",
        "entities": {
          "description": {
            "mentions": [
              {
                "end": 15,
                "start": 3,
                "username": "maoxian1527"
              },
              {
                "end": 83,
                "start": 71,
                "username": "maoxian2010"
              },
              {
                "end": 95,
                "start": 86,
                "username": "OuO_QwQg"
              },
              {
                "end": 107,
                "start": 98,
                "username": "Meph4786"
              },
              {
                "end": 123,
                "start": 111,
                "username": "tangeorange"
              },
              {
                "end": 136,
                "start": 127,
                "username": "Wilf_Lin"
              }
            ]
          },
          "url": {
            "urls": [
              {
                "display_url": "maoxianACT.top",
                "end": 23,
                "expanded_url": "http://maoxianACT.top",
                "start": 0,
                "url": "https://t.co/k5QWEwaHXn"
              }
            ]
          }
        },
        "id": "2029061443568713731",
        "location": "距离你13.14km🏳️‍⚧️",
        "name": "猫弦ACT ｡˖♡+ 🍥",
        "pinned_tweet_id": "2058799558457790678",
        "profile_image_url": "https://pbs.twimg.com/profile_images/2058797385028087808/xxRT3qZj_normal.jpg",
        "protected": false,
        "public_metrics": {
          "followers_count": 536,
          "following_count": 58,
          "like_count": 185,
          "listed_count": 3,
          "media_count": 84,
          "tweet_count": 319
        },
        "url": "https://t.co/k5QWEwaHXn",
        "username": "maoxianACT",
        "verified": false
      }
    ]
  }
}