{
  "data": {
    "article": {},
    "attachments": {},
    "author_id": "2047894021457211393",
    "conversation_id": "2065346640689426469",
    "created_at": "2026-06-13T14:18:01.000Z",
    "edit_controls": {
      "editable_until": "2026-06-13T15:18:01.000Z",
      "edits_remaining": 5,
      "is_edit_eligible": false
    },
    "edit_history_tweet_ids": [
      "2065800865345413392"
    ],
    "entities": {
      "mentions": [
        {
          "end": 12,
          "id": "1468567542264664067",
          "start": 0,
          "username": "Angelica_zj"
        }
      ]
    },
    "geo": {},
    "id": "2065800865345413392",
    "in_reply_to_user_id": "1468567542264664067",
    "lang": "zh",
    "note_tweet": {
      "entities": {}
    },
    "possibly_sensitive": false,
    "public_metrics": {
      "bookmark_count": 0,
      "impression_count": 0,
      "like_count": 0,
      "quote_count": 0,
      "reply_count": 0,
      "retweet_count": 0
    },
    "referenced_tweets": [
      {
        "id": "2065800562264707196",
        "type": "replied_to"
      }
    ],
    "reply_settings": "everyone",
    "text": "@Angelica_zj 我也有搞oc什麼的哦哦哦？！！但是但是就是不太枝豆布料什麼的要怎麼買喵（）求推薦qwq"
  },
  "includes": {
    "tweets": [
      {
        "article": {},
        "attachments": {},
        "author_id": "2047894021457211393",
        "conversation_id": "2065346640689426469",
        "created_at": "2026-06-13T14:18:01.000Z",
        "edit_controls": {
          "editable_until": "2026-06-13T15:18:01.000Z",
          "edits_remaining": 5,
          "is_edit_eligible": false
        },
        "edit_history_tweet_ids": [
          "2065800865345413392"
        ],
        "entities": {
          "mentions": [
            {
              "end": 12,
              "id": "1468567542264664067",
              "start": 0,
              "username": "Angelica_zj"
            }
          ]
        },
        "geo": {},
        "id": "2065800865345413392",
        "in_reply_to_user_id": "1468567542264664067",
        "lang": "zh",
        "note_tweet": {
          "entities": {}
        },
        "possibly_sensitive": false,
        "public_metrics": {
          "bookmark_count": 0,
          "impression_count": 0,
          "like_count": 0,
          "quote_count": 0,
          "reply_count": 0,
          "retweet_count": 0
        },
        "referenced_tweets": [
          {
            "id": "2065800562264707196",
            "type": "replied_to"
          }
        ],
        "reply_settings": "everyone",
        "text": "@Angelica_zj 我也有搞oc什麼的哦哦哦？！！但是但是就是不太枝豆布料什麼的要怎麼買喵（）求推薦qwq"
      },
      {
        "article": {},
        "attachments": {},
        "author_id": "1468567542264664067",
        "conversation_id": "2065346640689426469",
        "created_at": "2026-06-13T14:16:49.000Z",
        "edit_controls": {
          "editable_until": "2026-06-13T15:16:49.000Z",
          "edits_remaining": 5,
          "is_edit_eligible": false
        },
        "edit_history_tweet_ids": [
          "2065800562264707196"
        ],
        "entities": {
          "mentions": [
            {
              "end": 16,
              "id": "2047894021457211393",
              "start": 0,
              "username": "FanQie_QianQian"
            }
          ]
        },
        "geo": {},
        "id": "2065800562264707196",
        "in_reply_to_user_id": "2047894021457211393",
        "lang": "zh",
        "note_tweet": {
          "entities": {}
        },
        "possibly_sensitive": false,
        "public_metrics": {
          "bookmark_count": 0,
          "impression_count": 4,
          "like_count": 1,
          "quote_count": 0,
          "reply_count": 1,
          "retweet_count": 0
        },
        "referenced_tweets": [
          {
            "id": "2065799671814176838",
            "type": "replied_to"
          }
        ],
        "reply_settings": "everyone",
        "text": "@FanQie_QianQian 试试看！其实成本很低ww，不过不擅长缝制/画画的话可以找那种接努努一条龙服务的老师，价格也不会太高"
      }
    ],
    "users": [
      {
        "created_at": "2026-04-25T04:22:51.000Z",
        "description": "重生之8.0\n11年 順女 LGBTQ全友好 前世互關尋回\n另一個我@_FanQie11_\n寶寶 @7q46843886669",
        "entities": {
          "description": {
            "mentions": [
              {
                "end": 45,
                "start": 34,
                "username": "_FanQie11_"
              },
              {
                "end": 63,
                "start": 49,
                "username": "7q46843886669"
              }
            ]
          },
          "url": {
            "urls": [
              {
                "display_url": "ngl.link/_tomato._.fanq…",
                "end": 23,
                "expanded_url": "https://ngl.link/_tomato._.fanqie_1",
                "start": 0,
                "url": "https://t.co/JbrJBgq8ZL"
              }
            ]
          }
        },
        "id": "2047894021457211393",
        "name": "飯企鵝8.0",
        "pinned_tweet_id": "2051753420537954589",
        "profile_image_url": "https://pbs.twimg.com/profile_images/2057140948434649088/mo_BXY2p_normal.jpg",
        "protected": false,
        "public_metrics": {
          "followers_count": 819,
          "following_count": 60,
          "like_count": 2201,
          "listed_count": 1,
          "media_count": 80,
          "tweet_count": 957
        },
        "url": "https://t.co/JbrJBgq8ZL",
        "username": "FanQie_QianQian",
        "verified": false
      },
      {
        "created_at": "2021-12-08T13:06:19.000Z",
        "description": "烂画画的 / 请叫我小九，我爱你们 / shtwt发布均为库存，积极疗愈中 / 盗图死妈 / 祝各位生活顺利",
        "id": "1468567542264664067",
        "location": "暗黑螺旋女巫城堡🏰🪄💀",
        "name": "火星电子女巫",
        "pinned_tweet_id": "1657563635739430912",
        "profile_image_url": "https://pbs.twimg.com/profile_images/1634950497428971521/J5dGey3U_normal.jpg",
        "protected": false,
        "public_metrics": {
          "followers_count": 25087,
          "following_count": 1050,
          "like_count": 14850,
          "listed_count": 41,
          "media_count": 1595,
          "tweet_count": 17255
        },
        "username": "Angelica_zj",
        "verified": false
      }
    ]
  }
}